regex_rename/__init__.py
regex_rename/__main__.py
regex_rename/logging.py
regex_rename/main.py
regex_rename/match.py
regex_rename/params.py
regex_rename/py.typed
regex_rename/rename.py
regex_rename/version.py
regex_rename-1.3.3.dist-info/LICENSE
regex_rename-1.3.3.dist-info/METADATA
regex_rename-1.3.3.dist-info/WHEEL
regex_rename-1.3.3.dist-info/entry_points.txt
regex_rename-1.3.3.dist-info/top_level.txt
regex_rename-1.3.3.dist-info/RECORD
