Metadata-Version: 2.1
Name: regex-rename
Version: 1.3.3
Summary: Regular expressions bulk rename tool for multiple files
Author-email: igrek51 <igrek51.dev@gmail.com>
License: MIT
Project-URL: homepage, https://github.com/igrek51/regex-rename
Classifier: Programming Language :: Python :: 3
Classifier: License :: OSI Approved :: MIT License
Classifier: Operating System :: OS Independent
Requires-Python: >=3.7
License-File: LICENSE
Requires-Dist: nuclear >=2.1.0
Requires-Dist: colorama >=0.4.0
